pluginmaker/__init__.py
pluginmaker/cookiecutter_templates/__init__.py
pluginmaker/cookiecutter_templates/cmk_plugin/cookiecutter.json
pluginmaker/cookiecutter_templates/cmk_plugin/hooks/pre_gen_project.py
pluginmaker/cookiecutter_templates/cmk_plugin/setup.py
pluginmaker/cookiecutter_templates/cmk_plugin/{{cookiecutter.project_slug}}/Makefile
pluginmaker/cookiecutter_templates/cmk_plugin/{{cookiecutter.project_slug}}/agent_invoker/agent_{{cookiecutter.agent_id}}
pluginmaker/cookiecutter_templates/cmk_plugin/{{cookiecutter.project_slug}}/agent_special/agent_{{cookiecutter.agent_id}}
pluginmaker/cookiecutter_templates/cmk_plugin/{{cookiecutter.project_slug}}/mkp/config
pluginmaker/cookiecutter_templates/cmk_plugin/{{cookiecutter.project_slug}}/plugin/service_{{cookiecutter.agent_id}}.py
pluginmaker/cookiecutter_templates/cmk_plugin/{{cookiecutter.project_slug}}/wato/{{cookiecutter.agent_id}}_register.py
checkmkpluginmaker-2.0.2.dist-info/METADATA
checkmkpluginmaker-2.0.2.dist-info/WHEEL
checkmkpluginmaker-2.0.2.dist-info/entry_points.txt
checkmkpluginmaker-2.0.2.dist-info/RECORD
